{"web":{"client_id":"420004208749-7uvv65i1f51n0arfqub68rvg97mtr8oc.apps.googleusercontent.com","project_id":"likeit-4aace","auth_uri":"https://accounts.google.com/o/oauth2/auth","token_uri":"https://oauth2.googleapis.com/token","auth_provider_x509_cert_url":"https://www.googleapis.com/oauth2/v1/certs","client_secret":"FcruVTr6TRost_kazQwi9Rd1","redirect_uris":["https://likeit-4aace.firebaseapp.com/__/auth/handler"],"javascript_origins":["http://localhost","http://localhost:5000","https://likeit-4aace.firebaseapp.com"]}}